RTL/ALU/ALU.v
module ALU #(
    parameter DATA_WIDTH = 8
)
(
    input clk,
    input reset,
    input [DATA_WIDTH - 1:0] A,
    input [DATA_WIDTH - 1:0] B,
    input [3:0] ALU_function,
    input enable,
    
    output reg ALU_result_valid,
    output reg [2 * DATA_WIDTH - 1:0] ALU_result
);

    always @(posedge clk or negedge reset) begin
        if (~reset) begin
            ALU_result <= 'b0;
            ALU_result_valid <= 1'b0;
        end
        else begin
            if (enable) begin
                case (ALU_function)
                    4'b0000: begin
                        ALU_result <= A + B;
                        ALU_result_valid <= 1'b1;
                    end
                    4'b0001: begin
                        ALU_result <= A - B;
                        ALU_result_valid <= 1'b1;
                    end
                    4'b0010: begin
                        ALU_result <= A * B;
                        ALU_result_valid <= 1'b1;
                    end
                    4'b0011: begin
                        ALU_result <= A / B;
                        ALU_result_valid <= 1'b1;
                    end
                    4'b0100: begin
                        ALU_result <= A & B;
                        ALU_result_valid <= 1'b1;
                    end
                    4'b0101: begin
                        ALU_result <= A | B;
                        ALU_result_valid <= 1'b1;
                    end
                    4'b0110: begin
                        ALU_result <= ~(A & B);
                        ALU_result_valid <= 1'b1;
                    end
                    4'b0111: begin
                        ALU_result <= ~(A | B);
                        ALU_result_valid <= 1'b1;
                    end
                    4'b1000: begin
                        ALU_result <= A ^ B;
                        ALU_result_valid <= 1'b1;
                    end
                    4'b1001: begin
                        ALU_result <= ~(A ^ B);
                        ALU_result_valid <= 1'b1;
                    end
                    4'b1010: begin
                        if (A == B) begin
                            ALU_result <= 'b1;
                        end
                        else begin
                            ALU_result <= 'b0;
                        end
                        ALU_result_valid <= 1'b1;
                    end
                    4'b1011: begin
                        if (A > B) begin
                            ALU_result <= 'b1;
                        end
                        else begin
                            ALU_result <= 'b0;
                        end
                        ALU_result_valid <= 1'b1;
                    end
                    4'b1100: begin
                        if (A < B) begin
                            ALU_result <= 'b1;
                        end
                        else begin
                            ALU_result <= 'b0;
                        end
                        ALU_result_valid <= 1'b1;
                    end
                    4'b1101: begin
                        ALU_result <= A >> 1;
                        ALU_result_valid <= 1'b1;
                    end
                    4'b1110: begin
                        ALU_result <= A << 1;
                        ALU_result_valid <= 1'b1;
                    end
                    default: begin
                        ALU_result <= 'b0;
                        ALU_result_valid <= 1'b0;
                    end

                endcase
            end
            else begin
                ALU_result <= 'b0;
                ALU_result_valid <= 1'b0;
            end
            
        end
    end

endmodule

functional_verification/ALU/ALU_tb.v
`include "/home/naveensodad/Major_project/RTL/ALU/ALU.v"
`timescale 1ns/1ns

module ALU_tb ();

    localparam DATA_WIDTH = 8;
    localparam CLK_PERIOD = 25;

    // Input signals' declaration
    reg clk_tb;
    reg reset_tb;
    reg enable_tb;
    reg [DATA_WIDTH - 1:0] A_tb, B_tb;
    reg[3:0] ALU_function_tb;

    // Output signals' declaration
    wire ALU_result_valid_tb;
    wire [2 * DATA_WIDTH - 1:0] ALU_result_tb;

    integer file;
    integer passed_test_cases, total_test_cases;

    initial begin
        $timeformat(-9, 2, " ns", 20);
        file = $fopen("/home/naveensodad/output/ALU_output.txt", "w");
        passed_test_cases = 0;
        total_test_cases = 0;
	
    	$dumpfile("/home/naveensodad/Major_project/vcdfiles/ALU_wave.vcd");
    	$dumpvars(0, ALU_tb);


        initialize;
        reset;

        $display("--------------------- Test case (1) ---------------------");
        enable_tb = 1'b1;
        A_tb = 8'h54;
        B_tb = 8'h2A;
        ALU_function_tb = 4'b0000;
        #CLK_PERIOD
        if (ALU_result_tb == A_tb + B_tb) begin
            $fdisplay(file, "Test case (1) passed.");
            passed_test_cases = passed_test_cases + 1;
        end
        else begin
            $fdisplay(file, "Test case (1) failed.");
        end
        total_test_cases = total_test_cases + 1;
        $display("----------------------------------------------------------------");

        $display("--------------------- Test case (2) ---------------------");
        A_tb = 8'h54;
        B_tb = 8'h2A;
        ALU_function_tb = 4'b0001;
        #CLK_PERIOD
        if (ALU_result_tb == A_tb - B_tb) begin
            $fdisplay(file, "Test case (2) passed.");
            passed_test_cases = passed_test_cases + 1;
        end
        else begin
            $fdisplay(file, "Test case (2) failed.");
        end
        total_test_cases = total_test_cases + 1;
        $display("----------------------------------------------------------------");

        $display("--------------------- Test case (3) ---------------------");
        A_tb = 8'h54;
        B_tb = 8'h2A;
        ALU_function_tb = 4'b0010;
        #CLK_PERIOD
        if (ALU_result_tb == A_tb * B_tb) begin
            $fdisplay(file, "Test case (3) passed.");
            passed_test_cases = passed_test_cases + 1;
        end
        else begin
            $fdisplay(file, "Test case (3) failed.");
        end
        total_test_cases = total_test_cases + 1;
        $display("----------------------------------------------------------------");

        $display("--------------------- Test case (4) ---------------------");
        A_tb = 8'h54;
        B_tb = 8'h2A;
        ALU_function_tb = 4'b0011;
        #CLK_PERIOD
        if (ALU_result_tb == A_tb / B_tb) begin
            $fdisplay(file, "Test case (4) passed.");
            passed_test_cases = passed_test_cases + 1;
        end
        else begin
            $fdisplay(file, "Test case (4) failed.");
        end
        total_test_cases = total_test_cases + 1;
        $display("----------------------------------------------------------------");

        $display("--------------------- Test case (5) ---------------------");
        A_tb = 8'h54;
        B_tb = 8'h2F;
        ALU_function_tb = 4'b0100;
        #CLK_PERIOD
        if (ALU_result_tb == {8'b0, A_tb & B_tb}) begin
            $fdisplay(file, "Test case (5) passed.");
            passed_test_cases = passed_test_cases + 1;
        end
        else begin
            $fdisplay(file, "Test case (5) failed.");
        end
        total_test_cases = total_test_cases + 1;
        $display("----------------------------------------------------------------");

        $display("--------------------- Test case (6) ---------------------");
        A_tb = 8'hF4;
        B_tb = 8'h2C;
        ALU_function_tb = 4'b0101;
        #CLK_PERIOD
        if (ALU_result_tb == {8'b0, A_tb | B_tb}) begin
            $fdisplay(file, "Test case (6) passed.");
            passed_test_cases = passed_test_cases + 1;
        end
        else begin
            $fdisplay(file, "Test case (6) failed.");
        end
        total_test_cases = total_test_cases + 1;
        $display("----------------------------------------------------------------");
        
        $fdisplay(file, "Total: %0d/%0d.", passed_test_cases, total_test_cases);
        $stop;

end


    // Initialize all the input signals
    task initialize();
    begin
        clk_tb = 1'b0;
        enable_tb = 1'b0;
        A_tb = 'b0;
        B_tb = 'b0;
        ALU_function_tb = 4'b0000;
    end
    endtask

    // Reset the system in one clock cycle
    task reset();
    begin
        #CLK_PERIOD
        reset_tb = 1'b0;
        #CLK_PERIOD
        reset_tb = 1'b1;
    end
    endtask

    // Clock generator
    always #(CLK_PERIOD / 2.0) clk_tb = ~clk_tb;


    // Instantiate the ALU
    ALU # (
        .DATA_WIDTH(DATA_WIDTH)
    )
    U_ALU (
        .clk(clk_tb),
        .reset(reset_tb),
        .A(A_tb),
        .B(B_tb),
        .ALU_function(ALU_function_tb),
        .enable(enable_tb),

        .ALU_result_valid(ALU_result_valid_tb),
        .ALU_result(ALU_result_tb)
    );
endmodule

vcdfiles/ALU_wave.vcd
$date
	Thu May 15 00:23:45 2025
$end
$version
	Icarus Verilog
$end
$timescale
	1ns
$end
$scope module ALU_tb $end
$var wire 1 ! ALU_result_valid_tb $end
$var wire 16 " ALU_result_tb [15:0] $end
$var reg 4 # ALU_function_tb [3:0] $end
$var reg 8 $ A_tb [7:0] $end
$var reg 8 % B_tb [7:0] $end
$var reg 1 & clk_tb $end
$var reg 1 ' enable_tb $end
$var reg 1 ( reset_tb $end
$var integer 32 ) file [31:0] $end
$var integer 32 * passed_test_cases [31:0] $end
$var integer 32 + total_test_cases [31:0] $end
$scope module U_ALU $end
$var wire 8 , A [7:0] $end
$var wire 4 - ALU_function [3:0] $end
$var wire 8 . B [7:0] $end
$var wire 1 & clk $end
$var wire 1 ' enable $end
$var wire 1 ( reset $end
$var reg 16 / ALU_result [15:0] $end
$var reg 1 ! ALU_result_valid $end
$upscope $end
$scope task initialize $end
$upscope $end
$scope task reset $end
$upscope $end
$upscope $end
$enddefinitions $end
#0
$dumpvars
bx /
b0 .
b0 -
b0 ,
b0 +
b0 *
b0 )
x(
0'
0&
b0 %
b0 $
b0 #
bx "
x!
$end
#13
0!
b0 "
b0 /
1&
#25
0(
#26
0&
#39
1&
#50
b101010 %
b101010 .
b1010100 $
b1010100 ,
1'
1(
#52
0&
#65
1!
b1111110 "
b1111110 /
1&
#75
b1 #
b1 -
b1 +
b1 *
#78
0&
#91
b101010 "
b101010 /
1&
#100
b10 #
b10 -
b10 +
b10 *
#104
0&
#117
b110111001000 "
b110111001000 /
1&
#125
b11 #
b11 -
b11 +
b11 *
#130
0&
#143
b10 "
b10 /
1&
#150
b100 #
b100 -
b101111 %
b101111 .
b100 +
b100 *
#156
0&
#169
b100 "
b100 /
1&
#175
b101 #
b101 -
b101100 %
b101100 .
b11110100 $
b11110100 ,
b101 +
b101 *
#182
0&
#195
b11111100 "
b11111100 /
1&
