RTL/bus_synchronizer/register.v
module register #(
    parameter BUS_WIDTH = 1
)
(
    input clk,
    input reset,
    input [BUS_WIDTH - 1:0] D,

    output reg [BUS_WIDTH - 1:0] Q
);

    always @(posedge clk or negedge reset) begin
        if (~reset) begin
            Q <= 'b0;
        end
        else begin
            Q <= D;
        end
    end

endmodule

RTL/bus_synchronizer/bus_synchronizer.v
`include "/home/naveensodad/MAJOR_PROJECT/RTL/bus_synchronizer/register.v"

module bus_synchronizer #(
    parameter STAGE_COUNT = 2,
    parameter BUS_WIDTH = 1
)
(
    input clk,
    input reset,
    input [BUS_WIDTH - 1:0] asynchronous_data,

    output [BUS_WIDTH - 1:0] synchronous_data
);

    genvar i;
    wire [BUS_WIDTH - 1:0] output_ports [0:STAGE_COUNT - 1];

    register #(
        .BUS_WIDTH(BUS_WIDTH)
    )
    U0_register (
        .clk(clk),
        .reset(reset),
        .D(asynchronous_data),

        .Q(output_ports[0])
    );


    generate
        for (i = 1; i < STAGE_COUNT; i = i + 1) begin: register_instance
            register #(
                .BUS_WIDTH(BUS_WIDTH)
            ) 
            U_register (
                .clk(clk),
                .reset(reset),
                .D(output_ports[i - 1]),

                .Q(output_ports[i])
            );
        end
    endgenerate

    assign synchronous_data = output_ports[STAGE_COUNT - 1];

endmodule

functional_verification/bus_synchronizer/bus_synchronizer_tb.v
`include "/home/naveensodad/MAJOR_PROJECT/RTL/bus_synchronizer/bus_synchronizer.v"
`timescale 1ns/1ns

module bus_synchronizer_tb ();

    parameter STAGE_COUNT = 2;
    parameter BUS_WIDTH = 4;

    // The two clock periods should satisfy the following condition to ensure that
    // any generated data by the source stays constant for at least two cycles of 
    // destination's clock so that the synchronizer will be able to produce the correct
    // output after two clock cycles (in case it enters metastability, 
    // but in simulation this doesn't happen).
    // The condition: (SOURCE_CLK_PERIOD / 2) >= DESTINATION_CLK_PERIOD
    // Which is equivalent to: SOURCE_CLK_PERIOD >= 2 * DESTINATION_CLK_PERIOD
    // In simulation, the condition should be: SOURCE_CLK_PERIOD >= DESTINATION_CLK_PERIOD
    localparam SOURCE_CLK_PERIOD = 30;
    localparam DESTINATION_CLK_PERIOD = 12;


    // Read the gray codes from the external input file
    reg [BUS_WIDTH - 1:0] gray_codes [0:2 ** BUS_WIDTH - 1];


    // Input signals' declaration
    reg clk_tb;
    reg reset_tb;
    reg [BUS_WIDTH - 1:0] asynchronous_data_tb;


    // Output signals' declaration
    wire [BUS_WIDTH - 1:0] synchronous_data_tb;

    integer i, j;

    // Output file
    integer file;


    initial 
    begin
        
        $timeformat(-9, 2, " ns", 20);
        $readmemb("/home/naveensodad/MAJOR_PROJECT/input/gray_codes.txt", gray_codes);
        $monitor("time = %0t, synchronous_data = %b", $time, synchronous_data_tb);
        j = 0;
	$dumpfile("/home/naveensodad/MAJOR_PROJECT/vcdfiles/bus_synchronizer_dump.vcd");
	$dumpvars(0, bus_synchronizer_tb);
        initialize;
        reset;
        
        #(1.5 * DESTINATION_CLK_PERIOD);

        for (i = 1; i < 2 ** BUS_WIDTH; i = i + 1) begin
            asynchronous_data_tb <= gray_codes[i];
            // The data is generated from the source using its clock
            #SOURCE_CLK_PERIOD;
        end
    end

    always @(synchronous_data_tb) begin
        j = j + 1;
        if (j == 2 ** BUS_WIDTH) begin
            #(STAGE_COUNT * DESTINATION_CLK_PERIOD);
            $stop;
        end
    end

    // Initialize all the input signals
    task initialize();
    begin
        clk_tb = 1'b0;
        reset_tb = 1'b1;
        asynchronous_data_tb = 'b0;
    end
    endtask

    // Reset the system in one clock cycle
    task reset();
    begin
        #DESTINATION_CLK_PERIOD;
        reset_tb = 1'b0;
        #DESTINATION_CLK_PERIOD;
        reset_tb = 1'b1;
    end
    endtask

    // Destination clock generator
    always #(DESTINATION_CLK_PERIOD / 2.0) clk_tb = ~clk_tb;


    // DUT instantiation
    bus_synchronizer #(
        .STAGE_COUNT(STAGE_COUNT),
        .BUS_WIDTH(BUS_WIDTH)
    )
    U_bus_synchronizer (
        .clk(clk_tb),
        .reset(reset_tb),
        .asynchronous_data(asynchronous_data_tb),

        .synchronous_data(synchronous_data_tb)
    );

endmodule

vcdfiles/bus_synchronizer_dump.vcd
$date
	Thu May 15 20:12:30 2025
$end
$version
	Icarus Verilog
$end
$timescale
	1ns
$end
$scope module bus_synchronizer_tb $end
$var wire 4 ! synchronous_data_tb [3:0] $end
$var reg 4 " asynchronous_data_tb [3:0] $end
$var reg 1 # clk_tb $end
$var reg 1 $ reset_tb $end
$var integer 32 % i [31:0] $end
$var integer 32 & j [31:0] $end
$scope module U_bus_synchronizer $end
$var wire 4 ' asynchronous_data [3:0] $end
$var wire 1 # clk $end
$var wire 1 $ reset $end
$var wire 4 ( synchronous_data [3:0] $end
$scope begin register_instance[1] $end
$scope module U_register $end
$var wire 4 ) D [3:0] $end
$var wire 1 # clk $end
$var wire 1 $ reset $end
$var reg 4 * Q [3:0] $end
$upscope $end
$upscope $end
$scope module U0_register $end
$var wire 4 + D [3:0] $end
$var wire 1 # clk $end
$var wire 1 $ reset $end
$var reg 4 , Q [3:0] $end
$upscope $end
$upscope $end
$scope task initialize $end
$upscope $end
$scope task reset $end
$upscope $end
$upscope $end
$enddefinitions $end
#0
$dumpvars
bx ,
b0 +
bx *
bx )
bx (
b0 '
b0 &
bx %
1$
0#
b0 "
bx !
$end
#6
b0 )
b0 ,
1#
#12
b1 &
b0 !
b0 (
b0 *
0#
0$
#18
1#
#24
0#
1$
#30
1#
#36
0#
#42
b1 "
b1 '
b1 +
1#
b1 %
#48
0#
#54
b1 )
b1 ,
1#
#60
0#
#66
b10 &
b1 !
b1 (
b1 *
1#
#72
b11 "
b11 '
b11 +
0#
b10 %
#78
b11 )
b11 ,
1#
#84
0#
#90
b11 &
b11 !
b11 (
b11 *
1#
#96
0#
#102
b10 "
b10 '
b10 +
1#
b11 %
#108
0#
#114
b10 )
b10 ,
1#
#120
0#
#126
b100 &
b10 !
b10 (
b10 *
1#
#132
b110 "
b110 '
b110 +
0#
b100 %
#138
b110 )
b110 ,
1#
#144
0#
#150
b101 &
b110 !
b110 (
b110 *
1#
#156
0#
#162
b111 "
b111 '
b111 +
1#
b101 %
#168
0#
#174
b111 )
b111 ,
1#
#180
0#
#186
b110 &
b111 !
b111 (
b111 *
1#
#192
b101 "
b101 '
b101 +
0#
b110 %
#198
b101 )
b101 ,
1#
#204
0#
#210
b111 &
b101 !
b101 (
b101 *
1#
#216
0#
#222
b100 "
b100 '
b100 +
1#
b111 %
#228
0#
#234
b100 )
b100 ,
1#
#240
0#
#246
b1000 &
b100 !
b100 (
b100 *
1#
#252
b1100 "
b1100 '
b1100 +
0#
b1000 %
#258
b1100 )
b1100 ,
1#
#264
0#
#270
b1001 &
b1100 !
b1100 (
b1100 *
1#
#276
0#
#282
b1101 "
b1101 '
b1101 +
1#
b1001 %
#288
0#
#294
b1101 )
b1101 ,
1#
#300
0#
#306
b1010 &
b1101 !
b1101 (
b1101 *
1#
#312
b1111 "
b1111 '
b1111 +
0#
b1010 %
#318
b1111 )
b1111 ,
1#
#324
0#
#330
b1011 &
b1111 !
b1111 (
b1111 *
1#
#336
0#
#342
b1110 "
b1110 '
b1110 +
1#
b1011 %
#348
0#
#354
b1110 )
b1110 ,
1#
#360
0#
#366
b1100 &
b1110 !
b1110 (
b1110 *
1#
#372
b1010 "
b1010 '
b1010 +
0#
b1100 %
#378
b1010 )
b1010 ,
1#
#384
0#
#390
b1101 &
b1010 !
b1010 (
b1010 *
1#
#396
0#
#402
b1011 "
b1011 '
b1011 +
1#
b1101 %
#408
0#
#414
b1011 )
b1011 ,
1#
#420
0#
#426
b1110 &
b1011 !
b1011 (
b1011 *
1#
#432
b1001 "
b1001 '
b1001 +
0#
b1110 %
#438
b1001 )
b1001 ,
1#
#444
0#
#450
b1111 &
b1001 !
b1001 (
b1001 *
1#
#456
0#
#462
b1000 "
b1000 '
b1000 +
1#
b1111 %
#468
0#
#474
b1000 )
b1000 ,
1#
#480
0#
#486
b10000 &
b1000 !
b1000 (
b1000 *
1#
#492
0#
b10000 %
