RTL/clock_divider/clock_divider.v
module clock_divider (
    input reference_clk,
    input reset,
    input clk_divider_enable,
    input [5:0] division_ratio,

    output output_clk
);

    reg [4:0] counter;
    reg divided_clk;
    reg odd_toggle;
    wire [4:0] ratio_divided_by_two;
    wire enable;


    always @(posedge reference_clk or negedge reset) begin
        if (~reset) begin
            divided_clk <= 1'b0;
            odd_toggle <= 1'b1;
            counter <= 5'b0;
        end
        else if (enable) begin
            if (~division_ratio[0] & counter == ratio_divided_by_two - 1'b1) begin
                divided_clk <= ~divided_clk;
                counter <= 5'b0;
            end
            else if (division_ratio[0] & ((counter == ratio_divided_by_two - 1'b1 & odd_toggle)
                                        | (counter == ratio_divided_by_two & ~odd_toggle))) begin
                divided_clk <= ~divided_clk;
                odd_toggle <= ~odd_toggle;
                counter <= 5'b0;
            end
            else begin
                counter <= counter + 5'b1;
            end
        end
    end

    assign enable = clk_divider_enable & (division_ratio > 6'b00_0001);
    assign ratio_divided_by_two = (division_ratio >> 1);
    assign output_clk = clk_divider_enable ? divided_clk : reference_clk;

endmodule

functional_verification/clock_divider/clock_divider_tb.v
`include "/home/naveensodad/MAJOR_PROJECT/RTL/clock_divider/clock_divider.v"
`timescale 1ps / 1ps

module clock_divider_tb;

    reg reference_clk = 0;
    reg reset = 0;
    reg clk_divider_enable = 0;
    reg [5:0] division_ratio = 6'd0;
    wire output_clk;

    clock_divider uut (
        .reference_clk(reference_clk),
        .reset(reset),
        .clk_divider_enable(clk_divider_enable),
        .division_ratio(division_ratio),
        .output_clk(output_clk)
    );

    always #20 reference_clk = ~reference_clk;

    initial begin
        $dumpfile("/home/naveensodad/MAJOR_PROJECT/vcdfiles/clock_divider_dump.vcd");  // Output VCD
        $dumpvars(0, clock_divider_tb);

        // Reset
        reset = 0;
        #80;
        reset = 1;

        // Disabled initially
        clk_divider_enable = 0;
        #130;

        // Enable clock divider
        clk_divider_enable = 1;
        division_ratio = 6'd5;
        #830;

        division_ratio = 6'd3;
        #3000;

        division_ratio = 6'd8;
        #800;

        division_ratio = 6'd6;
        #800;

        $finish;
    end
endmodule

vcdfiles/clock_divider.vcd
$date
	Mon May 19 21:36:46 2025
$end
$version
	Icarus Verilog
$end
$timescale
	1ps
$end
$scope module clock_divider_tb $end
$var wire 1 ! output_clk $end
$var reg 1 " clk_divider_enable $end
$var reg 6 # division_ratio [5:0] $end
$var reg 1 $ reference_clk $end
$var reg 1 % reset $end
$scope module uut $end
$var wire 1 " clk_divider_enable $end
$var wire 6 & division_ratio [5:0] $end
$var wire 1 ' enable $end
$var wire 1 $ reference_clk $end
$var wire 1 % reset $end
$var wire 5 ( ratio_divided_by_two [4:0] $end
$var wire 1 ! output_clk $end
$var reg 5 ) counter [4:0] $end
$var reg 1 * divided_clk $end
$var reg 1 + odd_toggle $end
$upscope $end
$upscope $end
$enddefinitions $end
#0
$dumpvars
1+
0*
b0 )
b0 (
0'
b0 &
0%
0$
b0 #
0"
0!
$end
#20
1!
1$
#40
0!
0$
#60
1!
1$
#80
0!
0$
1%
#100
1!
1$
#120
0!
0$
#140
1!
1$
#160
0!
0$
#180
1!
1$
#200
0!
0$
#210
b10 (
1'
b101 #
b101 &
1"
#220
b1 )
1$
#240
0$
#260
1!
0+
1*
b0 )
1$
#280
0$
#300
b1 )
1$
#320
0$
#340
b10 )
1$
#360
0$
#380
0!
1+
0*
b0 )
1$
#400
0$
#420
b1 )
1$
#440
0$
#460
1!
0+
1*
b0 )
1$
#480
0$
#500
b1 )
1$
#520
0$
#540
b10 )
1$
#560
0$
#580
0!
1+
0*
b0 )
1$
#600
0$
#620
b1 )
1$
#640
0$
#660
1!
0+
1*
b0 )
1$
#680
0$
#700
b1 )
1$
#720
0$
#740
b10 )
1$
#760
0$
#780
0!
1+
0*
b0 )
1$
#800
0$
#820
b1 )
1$
#840
0$
#860
1!
0+
1*
b0 )
1$
#880
0$
#900
b1 )
1$
#920
0$
#940
b10 )
1$
#960
0$
#980
0!
1+
0*
b0 )
1$
#1000
0$
#1020
b1 )
1$
#1040
b1 (
0$
b11 #
b11 &
#1060
b10 )
1$
#1080
0$
#1100
b11 )
1$
#1120
0$
#1140
b100 )
1$
#1160
0$
#1180
b101 )
1$
#1200
0$
#1220
b110 )
1$
#1240
0$
#1260
b111 )
1$
#1280
0$
#1300
b1000 )
1$
#1320
0$
#1340
b1001 )
1$
#1360
0$
#1380
b1010 )
1$
#1400
0$
#1420
b1011 )
1$
#1440
0$
#1460
b1100 )
1$
#1480
0$
#1500
b1101 )
1$
#1520
0$
#1540
b1110 )
1$
#1560
0$
#1580
b1111 )
1$
#1600
0$
#1620
b10000 )
1$
#1640
0$
#1660
b10001 )
1$
#1680
0$
#1700
b10010 )
1$
#1720
0$
#1740
b10011 )
1$
#1760
0$
#1780
b10100 )
1$
#1800
0$
#1820
b10101 )
1$
#1840
0$
#1860
b10110 )
1$
#1880
0$
#1900
b10111 )
1$
#1920
0$
#1940
b11000 )
1$
#1960
0$
#1980
b11001 )
1$
#2000
0$
#2020
b11010 )
1$
#2040
0$
#2060
b11011 )
1$
#2080
0$
#2100
b11100 )
1$
#2120
0$
#2140
b11101 )
1$
#2160
0$
#2180
b11110 )
1$
#2200
0$
#2220
b11111 )
1$
#2240
0$
#2260
b0 )
1$
#2280
0$
#2300
1!
0+
1*
b0 )
1$
#2320
0$
#2340
b1 )
1$
#2360
0$
#2380
0!
1+
0*
b0 )
1$
#2400
0$
#2420
1!
0+
1*
b0 )
1$
#2440
0$
#2460
b1 )
1$
#2480
0$
#2500
0!
1+
0*
b0 )
1$
#2520
0$
#2540
1!
0+
1*
b0 )
1$
#2560
0$
#2580
b1 )
1$
#2600
0$
#2620
0!
1+
0*
b0 )
1$
#2640
0$
#2660
1!
0+
1*
b0 )
1$
#2680
0$
#2700
b1 )
1$
#2720
0$
#2740
0!
1+
0*
b0 )
1$
#2760
0$
#2780
1!
0+
1*
b0 )
1$
#2800
0$
#2820
b1 )
1$
#2840
0$
#2860
0!
1+
0*
b0 )
1$
#2880
0$
#2900
1!
0+
1*
b0 )
1$
#2920
0$
#2940
b1 )
1$
#2960
0$
#2980
0!
1+
0*
b0 )
1$
#3000
0$
#3020
1!
0+
1*
b0 )
1$
#3040
0$
#3060
b1 )
1$
#3080
0$
#3100
0!
1+
0*
b0 )
1$
#3120
0$
#3140
1!
0+
1*
b0 )
1$
#3160
0$
#3180
b1 )
1$
#3200
0$
#3220
0!
1+
0*
b0 )
1$
#3240
0$
#3260
1!
0+
1*
b0 )
1$
#3280
0$
#3300
b1 )
1$
#3320
0$
#3340
0!
1+
0*
b0 )
1$
#3360
0$
#3380
1!
0+
1*
b0 )
1$
#3400
0$
#3420
b1 )
1$
#3440
0$
#3460
0!
1+
0*
b0 )
1$
#3480
0$
#3500
1!
0+
1*
b0 )
1$
#3520
0$
#3540
b1 )
1$
#3560
0$
#3580
0!
1+
0*
b0 )
1$
#3600
0$
#3620
1!
0+
1*
b0 )
1$
#3640
0$
#3660
b1 )
1$
#3680
0$
#3700
0!
1+
0*
b0 )
1$
#3720
0$
#3740
1!
0+
1*
b0 )
1$
#3760
0$
#3780
b1 )
1$
#3800
0$
#3820
0!
1+
0*
b0 )
1$
#3840
0$
#3860
1!
0+
1*
b0 )
1$
#3880
0$
#3900
b1 )
1$
#3920
0$
#3940
0!
1+
0*
b0 )
1$
#3960
0$
#3980
1!
0+
1*
b0 )
1$
#4000
0$
#4020
b1 )
1$
#4040
b100 (
0$
b1000 #
b1000 &
#4060
b10 )
1$
#4080
0$
#4100
b11 )
1$
#4120
0$
#4140
0!
0*
b0 )
1$
#4160
0$
#4180
b1 )
1$
#4200
0$
#4220
b10 )
1$
#4240
0$
#4260
b11 )
1$
#4280
0$
#4300
1!
1*
b0 )
1$
#4320
0$
#4340
b1 )
1$
#4360
0$
#4380
b10 )
1$
#4400
0$
#4420
b11 )
1$
#4440
0$
#4460
0!
0*
b0 )
1$
#4480
0$
#4500
b1 )
1$
#4520
0$
#4540
b10 )
1$
#4560
0$
#4580
b11 )
1$
#4600
0$
#4620
1!
1*
b0 )
1$
#4640
0$
#4660
b1 )
1$
#4680
0$
#4700
b10 )
1$
#4720
0$
#4740
b11 )
1$
#4760
0$
#4780
0!
0*
b0 )
1$
#4800
0$
#4820
b1 )
1$
#4840
b11 (
0$
b110 #
b110 &
#4860
b10 )
1$
#4880
0$
#4900
1!
1*
b0 )
1$
#4920
0$
#4940
b1 )
1$
#4960
0$
#4980
b10 )
1$
#5000
0$
#5020
0!
0*
b0 )
1$
#5040
0$
#5060
b1 )
1$
#5080
0$
#5100
b10 )
1$
#5120
0$
#5140
1!
1*
b0 )
1$
#5160
0$
#5180
b1 )
1$
#5200
0$
#5220
b10 )
1$
#5240
0$
#5260
0!
0*
b0 )
1$
#5280
0$
#5300
b1 )
1$
#5320
0$
#5340
b10 )
1$
#5360
0$
#5380
1!
1*
b0 )
1$
#5400
0$
#5420
b1 )
1$
#5440
0$
#5460
b10 )
1$
#5480
0$
#5500
0!
0*
b0 )
1$
#5520
0$
#5540
b1 )
1$
#5560
0$
#5580
b10 )
1$
#5600
0$
#5620
1!
1*
b0 )
1$
