RTL/bus_synchronizer/register.v
module register #(
    parameter BUS_WIDTH = 1
)
(
    input clk,
    input reset,
    input [BUS_WIDTH - 1:0] D,

    output reg [BUS_WIDTH - 1:0] Q
);

    always @(posedge clk or negedge reset) begin
        if (~reset) begin
            Q <= 'b0;
        end
        else begin
            Q <= D;
        end
    end

endmodule

RTL/bus_synchronizer/bus_synchronizer.v
`include "/home/naveensodad/MAJOR_PROJECT/RTL/bus_synchronizer/register.v"

module bus_synchronizer #(
    parameter STAGE_COUNT = 2,
    parameter BUS_WIDTH = 1
)
(
    input clk,
    input reset,
    input [BUS_WIDTH - 1:0] asynchronous_data,

    output [BUS_WIDTH - 1:0] synchronous_data
);

    genvar i;
    wire [BUS_WIDTH - 1:0] output_ports [0:STAGE_COUNT - 1];

    register #(
        .BUS_WIDTH(BUS_WIDTH)
    )
    U0_register (
        .clk(clk),
        .reset(reset),
        .D(asynchronous_data),

        .Q(output_ports[0])
    );


    generate
        for (i = 1; i < STAGE_COUNT; i = i + 1) begin: register_instance
            register #(
                .BUS_WIDTH(BUS_WIDTH)
            ) 
            U_register (
                .clk(clk),
                .reset(reset),
                .D(output_ports[i - 1]),

                .Q(output_ports[i])
            );
        end
    endgenerate

    assign synchronous_data = output_ports[STAGE_COUNT - 1];

endmodule

RTL/data_synchronizer/data_synchronizer.v
`include "/home/naveensodad/Major_project/RTL/bus_synchronizer/bus_synchronizer.v"
`include "../bus_synchronizer/bus_synchronizer.v"

module data_synchronizer #(
    parameter STAGE_COUNT = 2,
    parameter BUS_WIDTH = 8
)
(
    input clk,
    input reset,
    input asynchronous_data_valid,
    input [BUS_WIDTH - 1:0] asynchronous_data,

    output reg Q_pulse_generator,
    output reg synchronous_data_valid,
    output reg [BUS_WIDTH - 1:0] synchronous_data
);

    wire synchronized_enable;
    wire pulse_generator_output;

    // Bit synchronizer to synchronize the data valid signal
    bus_synchronizer #(
        .STAGE_COUNT(STAGE_COUNT),
        .BUS_WIDTH(1)
    )
    U_bus_synchronizer (
        .clk(clk),
        .reset(reset),
        .asynchronous_data(asynchronous_data_valid),

        .synchronous_data(synchronized_enable)
    );


    // Pulse generator register
    always @(posedge clk or negedge reset) begin
        if (~reset) begin
            Q_pulse_generator <= 1'b0;
        end
        else begin
            Q_pulse_generator <= synchronized_enable;
        end
    end
    assign pulse_generator_output = synchronized_enable & (~Q_pulse_generator);


    // Data valid register
    always @(posedge clk or negedge reset) begin
        if (~reset) begin
            synchronous_data_valid <= 1'b0;
        end
        else begin
            synchronous_data_valid <= pulse_generator_output;
        end
    end

    // Synchronized data register
    always @(posedge clk or negedge reset) begin
        if (~reset) begin
            synchronous_data <= 'b0;
        end
        else if (pulse_generator_output) begin
            synchronous_data <= asynchronous_data;
        end
    end


endmodule

functional_verification/data_synchronizer/data_synchronizer_tb.v
`include "/home/naveensodad/MAJOR_PROJECT/RTL/data_synchronizer/data_synchronizer.v"

module data_synchronizer_tb ();
    parameter STAGE_COUNT = 2;
    parameter BUS_WIDTH = 4;

    
    localparam SOURCE_CLK_PERIOD = 50;
    localparam DESTINATION_CLK_PERIOD = 12;


    // Read the input data codes from the external input file
    reg [BUS_WIDTH - 1:0] input_data [0:2 ** BUS_WIDTH - 1];

    // Input signals' declaration
    reg destination_clk_tb;
    reg reset_tb;
    reg asynchronous_data_valid_tb;
    reg [BUS_WIDTH - 1:0] asynchronous_data_tb;


    // Output signals' declaration
    wire [BUS_WIDTH - 1:0] synchronous_data_tb;
    wire synchronous_data_valid_tb;
    wire Q_pulse_generator_tb;

    integer i, j, k;
    integer passed_test_cases;
    integer total_test_cases;

    // Output file
    integer file;


    initial 
    begin
        $timeformat(-9, 2, " ns", 20);
        $readmemb("/home/naveensodad/MAJOR_PROJECT/functional_verification/data_synchronizer/inputs.txt", input_data);        
        file = $fopen("/home/naveensodad/MAJOR_PROJECT/output/data_synchronizer_output.txt", "w");
        total_test_cases = 2 ** BUS_WIDTH;
        passed_test_cases = 0;
        initialize();
        reset();
        $dumpfile("/home/naveensodad/MAJOR_PROJECT/vcdfiles/data_synchronizer_dump.vcd");
	$dumpvars(0, data_synchronizer_tb); 

        for (i = 0; i < 2 ** BUS_WIDTH; i = i + 1) begin
            asynchronous_data_tb = input_data[i];
            asynchronous_data_valid_tb = 1'b1;

            @(posedge synchronous_data_valid_tb);
            if (synchronous_data_tb == asynchronous_data_tb) begin
                $fdisplay(file, "Test case (%0d) passed.", i + 1);
                passed_test_cases = passed_test_cases + 1;
            end
            else begin
                $fdisplay(file, "Test case (%0d) failed.", i + 1);
            end
            asynchronous_data_valid_tb = 1'b0;
            #SOURCE_CLK_PERIOD;
        end
        $fdisplay(file, "Total: %0d/%0d.", passed_test_cases, total_test_cases);
        $stop;
    end


    // Initialize all the input signals
    task initialize();
    begin
        destination_clk_tb = 1'b0;
        reset_tb = 1'b1;
        asynchronous_data_valid_tb = 1'b0;
        asynchronous_data_tb = 'b0;
    end
    endtask

    // Reset the system in one clock cycle
    task reset();
    begin
        #DESTINATION_CLK_PERIOD;
        reset_tb = 1'b0;
        #DESTINATION_CLK_PERIOD;
        reset_tb = 1'b1;
    end
    endtask

    // Destination clock generator
    always #(DESTINATION_CLK_PERIOD / 2.0) destination_clk_tb = ~destination_clk_tb;



    // DUT instantiation
    data_synchronizer #(
        .STAGE_COUNT(STAGE_COUNT),
        .BUS_WIDTH(BUS_WIDTH)
    )
    U_data_synchronizer (
        .clk(destination_clk_tb),
        .reset(reset_tb),
        .asynchronous_data_valid(asynchronous_data_valid_tb),
        .asynchronous_data(asynchronous_data_tb),

        .Q_pulse_generator(Q_pulse_generator_tb),
        .synchronous_data(synchronous_data_tb),
        .synchronous_data_valid(synchronous_data_valid_tb)
    );
endmodule

vcdfiles/data_synchronizer_dump.vcd
$date
	Thu May 15 22:53:52 2025
$end
$version
	Icarus Verilog
$end
$timescale
	1s
$end
$scope module data_synchronizer_tb $end
$var wire 1 ! synchronous_data_valid_tb $end
$var wire 4 " synchronous_data_tb [3:0] $end
$var wire 1 # Q_pulse_generator_tb $end
$var reg 4 $ asynchronous_data_tb [3:0] $end
$var reg 1 % asynchronous_data_valid_tb $end
$var reg 1 & destination_clk_tb $end
$var reg 1 ' reset_tb $end
$var integer 32 ( file [31:0] $end
$var integer 32 ) i [31:0] $end
$var integer 32 * passed_test_cases [31:0] $end
$var integer 32 + total_test_cases [31:0] $end
$scope module U_data_synchronizer $end
$var wire 4 , asynchronous_data [3:0] $end
$var wire 1 % asynchronous_data_valid $end
$var wire 1 & clk $end
$var wire 1 - pulse_generator_output $end
$var wire 1 ' reset $end
$var wire 1 . synchronized_enable $end
$var reg 1 # Q_pulse_generator $end
$var reg 4 / synchronous_data [3:0] $end
$var reg 1 ! synchronous_data_valid $end
$scope module U_bus_synchronizer $end
$var wire 1 % asynchronous_data $end
$var wire 1 & clk $end
$var wire 1 ' reset $end
$var wire 1 . synchronous_data $end
$scope begin register_instance[1] $end
$scope module U_register $end
$var wire 1 0 D $end
$var wire 1 & clk $end
$var wire 1 ' reset $end
$var reg 1 1 Q $end
$upscope $end
$upscope $end
$scope module U0_register $end
$var wire 1 % D $end
$var wire 1 & clk $end
$var wire 1 ' reset $end
$var reg 1 0 Q $end
$upscope $end
$upscope $end
$upscope $end
$scope task initialize $end
$upscope $end
$scope task reset $end
$upscope $end
$upscope $end
$enddefinitions $end
#24
$dumpvars
01
00
b0 /
0.
0-
b1110 ,
b10000 +
b0 *
b0 )
b10000000000000000000000000000011 (
1'
0&
1%
b1110 $
0#
b0 "
0!
$end
#30
10
1&
#36
0&
#42
1-
1.
11
1&
#48
0&
#54
0-
0%
b1 *
b1110 "
b1110 /
1!
1#
1&
#60
0&
#66
00
0!
1&
#72
0&
#78
0.
01
1&
#84
0&
#90
0#
1&
#96
0&
#102
1&
#104
1%
b1001 $
b1001 ,
b1 )
#108
0&
#114
10
1&
#120
0&
#126
1-
1.
11
1&
#132
0&
#138
0-
0%
b10 *
1#
1!
b1001 "
b1001 /
1&
#144
0&
#150
0!
00
1&
#156
0&
#162
0.
01
1&
#168
0&
#174
0#
1&
#180
0&
#186
1&
#188
1%
b0 $
b0 ,
b10 )
#192
0&
#198
10
1&
#204
0&
#210
1-
1.
11
1&
#216
0&
#222
0-
0%
b11 *
b0 "
b0 /
1!
1#
1&
#228
0&
#234
00
0!
1&
#240
0&
#246
0.
01
1&
#252
0&
#258
0#
1&
#264
0&
#270
1&
#272
1%
b1 $
b1 ,
b11 )
#276
0&
#282
10
1&
#288
0&
#294
1-
1.
11
1&
#300
0&
#306
0-
0%
b100 *
1#
1!
b1 "
b1 /
1&
#312
0&
#318
0!
00
1&
#324
0&
#330
0.
01
1&
#336
0&
#342
0#
1&
#348
0&
#354
1&
#356
1%
b11 $
b11 ,
b100 )
#360
0&
#366
10
1&
#372
0&
#378
1-
1.
11
1&
#384
0&
#390
0-
0%
b101 *
b11 "
b11 /
1!
1#
1&
#396
0&
#402
00
0!
1&
#408
0&
#414
0.
01
1&
#420
0&
#426
0#
1&
#432
0&
#438
1&
#440
1%
b1101 $
b1101 ,
b101 )
#444
0&
#450
10
1&
#456
0&
#462
1-
1.
11
1&
#468
0&
#474
0-
0%
b110 *
1#
1!
b1101 "
b1101 /
1&
#480
0&
#486
0!
00
1&
#492
0&
#498
0.
01
1&
#504
0&
#510
0#
1&
#516
0&
#522
1&
#524
1%
b1100 $
b1100 ,
b110 )
#528
0&
#534
10
1&
#540
0&
#546
1-
1.
11
1&
#552
0&
#558
0-
0%
b111 *
b1100 "
b1100 /
1!
1#
1&
#564
0&
#570
00
0!
1&
#576
0&
#582
0.
01
1&
#588
0&
#594
0#
1&
#600
0&
#606
1&
#608
1%
b110 $
b110 ,
b111 )
#612
0&
#618
10
1&
#624
0&
#630
1-
1.
11
1&
#636
0&
#642
0-
0%
b1000 *
1#
1!
b110 "
b110 /
1&
#648
0&
#654
0!
00
1&
#660
0&
#666
0.
01
1&
#672
0&
#678
0#
1&
#684
0&
#690
1&
#692
1%
b1000 $
b1000 ,
b1000 )
#696
0&
#702
10
1&
#708
0&
#714
1-
1.
11
1&
#720
0&
#726
0-
0%
b1001 *
b1000 "
b1000 /
1!
1#
1&
#732
0&
#738
00
0!
1&
#744
0&
#750
0.
01
1&
#756
0&
#762
0#
1&
#768
0&
#774
1&
#776
1%
b100 $
b100 ,
b1001 )
#780
0&
#786
10
1&
#792
0&
#798
1-
1.
11
1&
#804
0&
#810
0-
0%
b1010 *
1#
1!
b100 "
b100 /
1&
#816
0&
#822
0!
00
1&
#828
0&
#834
0.
01
1&
#840
0&
#846
0#
1&
#852
0&
#858
1&
#860
1%
b1111 $
b1111 ,
b1010 )
#864
0&
#870
10
1&
#876
0&
#882
1-
1.
11
1&
#888
0&
#894
0-
0%
b1011 *
b1111 "
b1111 /
1!
1#
1&
#900
0&
#906
00
0!
1&
#912
0&
#918
0.
01
1&
#924
0&
#930
0#
1&
#936
0&
#942
1&
#944
1%
b10 $
b10 ,
b1011 )
#948
0&
#954
10
1&
#960
0&
#966
1-
1.
11
1&
#972
0&
#978
0-
0%
b1100 *
1#
1!
b10 "
b10 /
1&
#984
0&
#990
0!
00
1&
#996
0&
#1002
0.
01
1&
#1008
0&
#1014
0#
1&
#1020
0&
#1026
1&
#1028
1%
b1011 $
b1011 ,
b1100 )
#1032
0&
#1038
10
1&
#1044
0&
#1050
1-
1.
11
1&
#1056
0&
#1062
0-
0%
b1101 *
b1011 "
b1011 /
1!
1#
1&
#1068
0&
#1074
00
0!
1&
#1080
0&
#1086
0.
01
1&
#1092
0&
#1098
0#
1&
#1104
0&
#1110
1&
#1112
1%
b101 $
b101 ,
b1101 )
#1116
0&
#1122
10
1&
#1128
0&
#1134
1-
1.
11
1&
#1140
0&
#1146
0-
0%
b1110 *
1#
1!
b101 "
b101 /
1&
#1152
0&
#1158
0!
00
1&
#1164
0&
#1170
0.
01
1&
#1176
0&
#1182
0#
1&
#1188
0&
#1194
1&
#1196
1%
b1010 $
b1010 ,
b1110 )
#1200
0&
#1206
10
1&
#1212
0&
#1218
1-
1.
11
1&
#1224
0&
#1230
0-
0%
b1111 *
b1010 "
b1010 /
1!
1#
1&
#1236
0&
#1242
00
0!
1&
#1248
0&
#1254
0.
01
1&
#1260
0&
#1266
0#
1&
#1272
0&
#1278
1&
#1280
1%
b111 $
b111 ,
b1111 )
#1284
0&
#1290
10
1&
#1296
0&
#1302
1-
1.
11
1&
#1308
0&
#1314
0-
0%
b10000 *
1#
1!
b111 "
b111 /
1&
#1320
0&
#1326
0!
00
1&
#1332
0&
#1338
0.
01
1&
#1344
0&
#1350
0#
1&
