RTL/reset_synchronizer/reset_synchronizer.v
module reset_synchronizer #(
    parameter STAGE_COUNT = 2
)
(
    input clk,
    input reset,

    output reset_synchronized
);

    reg [0:STAGE_COUNT - 1] Q;
    integer i;

    always @(posedge clk or negedge reset) begin
        if (~reset) begin
            Q <= 'b0;
        end
        else begin
            Q[0] <= 1'b1;
            for (i = 1; i < STAGE_COUNT; i = i + 1) begin
                Q[i] <= Q[i - 1];
            end
        end
    end

    assign reset_synchronized = Q[STAGE_COUNT - 1];

endmodule

functional_verification/reset_synchronizer/reset_synchronizer_tb.v
`include "/home/naveensodad/MAJOR_PROJECT/RTL/reset_synchronizer/reset_synchronizer.v"
`timescale 1ps / 1ps

module reset_synchronizer_tb;

    // Inputs
    reg clk = 0;
    reg reset = 0;

    // Output
    wire reset_synchronized;

    // Instantiate the DUT (Device Under Test)
    reset_synchronizer #(
        .STAGE_COUNT(2)
    ) uut (
        .clk(clk),
        .reset(reset),
        .reset_synchronized(reset_synchronized)
    );

    // Clock generation: 50% duty cycle, 20ps period
    always #10 clk = ~clk;

    initial begin
        // Generate waveform dump
        $dumpfile("/home/naveensodad/MAJOR_PROJECT/vcdfiles/reset_synchronizer.vcd");
        $dumpvars(0, reset_synchronizer_tb);

        // Test sequence

        // Initial state
        reset = 0;
        #25;

        // First deassertion of reset
        reset = 1;
        #49;

        // Assert reset again
        reset = 0;
        #24;

        // Deassert reset again
        reset = 1;
        #39;

        // Pulse reset again
        reset = 0;
        #86;

        // Deassert
        reset = 1;
        #28;

        // Again reset pulse
        reset = 0;
        #43;

        // Deassert reset
        reset = 1;
        #29;

        // Reset again
        reset = 0;
        #86;

        // Deassert one last time
        reset = 1;
        #39;

        // Final reset
        reset = 0;
        #86;

        // Finish simulation
        $finish;
    end

endmodule

vcdfiles/reset_synchronizer_dump.vcd
$date
	Thu May 15 22:39:07 2025
$end
$version
	Icarus Verilog
$end
$timescale
	1ps
$end
$scope module reset_synchronizer_tb $end
$var wire 1 ! reset_synchronized $end
$var reg 1 " clk $end
$var reg 1 # reset $end
$scope module uut $end
$var wire 1 " clk $end
$var wire 1 # reset $end
$var wire 1 ! reset_synchronized $end
$var reg 2 $ Q [0:1] $end
$var integer 32 % i [31:0] $end
$upscope $end
$upscope $end
$enddefinitions $end
#0
$dumpvars
bx %
b0 $
0#
0"
0!
$end
#10
1"
#20
0"
#25
1#
#30
b10 $
b10 %
1"
#40
0"
#50
1!
b11 $
b10 %
1"
#60
0"
#70
b10 %
1"
#74
0!
b0 $
0#
#80
0"
#90
1"
#98
1#
#100
0"
#110
b10 $
b10 %
1"
#120
0"
#130
1!
b11 $
b10 %
1"
#137
0!
b0 $
0#
#140
0"
#150
1"
#160
0"
#170
1"
#180
0"
#190
1"
#200
0"
#210
1"
#220
0"
#223
1#
#230
b10 $
b10 %
1"
#240
0"
#250
1!
b11 $
b10 %
1"
#251
0!
b0 $
0#
#260
0"
#270
1"
#280
0"
#290
1"
#294
1#
#300
0"
#310
b10 $
b10 %
1"
#320
0"
#323
b0 $
0#
#330
1"
#340
0"
#350
1"
#360
0"
#370
1"
#380
0"
#390
1"
#400
0"
#409
1#
#410
b10 $
b10 %
1"
#420
0"
#430
1!
b11 $
b10 %
1"
#440
0"
#448
0!
b0 $
0#
